hw2/cnt/cnt_en_clr.v
module cnt_en_clr #(
    parameter CNT_WIDTH = 2
) (
    input clk_i,
    input arstn_i,
    input cnt_en_i,
    input cnt_clr_i,
    
    output [CNT_WIDTH-1:0] cnt_o,
    output ovf_o
);
    reg [CNT_WIDTH:0] cnt_ff;

    always @(posedge clk_i or negedge arstn_i) begin
        if (!arstn_i | cnt_clr_i) begin
            cnt_ff <= {CNT_WIDTH+1{1'b0}};
        end else begin
            cnt_ff <= cnt_en_i ? cnt_ff + 1 : cnt_ff;
        end
    end

    assign {ovf_o, cnt_o} = cnt_ff;
endmodule

hw2/cnt/cnt_en_clr_tb.v
`timescale 1ns/1ps

module cnt_en_clr_tb();
    localparam CNT_WIDTH = 2;

    reg clk_i;
    reg arstn_i;
    reg cnt_en_i;
    reg cnt_clr_i;
    
    wire [CNT_WIDTH-1:0] cnt_o;
    wire ovf_o;

    cnt_en_clr #(
        .CNT_WIDTH(CNT_WIDTH)
    ) cnt_en_clr_inst (
        .clk_i    (clk_i    ),
        .arstn_i  (arstn_i  ),
        .cnt_en_i (cnt_en_i ),
        .cnt_clr_i(cnt_clr_i),

        .cnt_o (cnt_o),
        .ovf_o (ovf_o)
    );

    always begin
        clk_i = 1'b0; #1;
        clk_i = 1'b1; #1;
    end

    initial begin
        $dumpvars;
        arstn_i   = 1'b1;
        cnt_en_i  = 1'b0;
        cnt_clr_i = 1'b0;

        @(posedge clk_i); #0.5;
        arstn_i = 1'b0;

        @(posedge clk_i); #0.5;
        arstn_i = 1'b1;

        @(posedge clk_i); #0.5;
        cnt_en_i  = 1'b1; #2;
        @(posedge clk_i);
        @(posedge clk_i); #0.5;
        cnt_en_i  = 1'b0; #2;
        @(posedge clk_i); #0.5;
        cnt_en_i  = 1'b1;

        @(posedge clk_i); #0.5;
        cnt_clr_i  = 1'b1;
        @(posedge clk_i); #1.5;
        cnt_clr_i  = 1'b0; #10;
        @(posedge clk_i); #0.5;
        $finish;
    end


endmodule

hw2/cnt/dump.vcd
$date
	Fri Mar 28 13:28:52 2025
$end
$version
	Icarus Verilog
$end
$timescale
	1ps
$end
$scope module cnt_en_clr_tb $end
$var wire 1 ! ovf_o $end
$var wire 2 " cnt_o [1:0] $end
$var parameter 32 # CNT_WIDTH $end
$var reg 1 $ arstn_i $end
$var reg 1 % clk_i $end
$var reg 1 & cnt_clr_i $end
$var reg 1 ' cnt_en_i $end
$scope module cnt_en_clr_inst $end
$var wire 1 $ arstn_i $end
$var wire 1 % clk_i $end
$var wire 1 & cnt_clr_i $end
$var wire 1 ' cnt_en_i $end
$var wire 1 ! ovf_o $end
$var wire 2 ( cnt_o [1:0] $end
$var parameter 32 ) CNT_WIDTH $end
$var reg 3 * cnt_ff [2:0] $end
$upscope $end
$upscope $end
$enddefinitions $end
$comment Show the parameter values. $end
$dumpall
b10 )
b10 #
$end
#0
$dumpvars
bx *
bx (
0'
0&
0%
1$
bx "
x!
$end
#1000
1%
#1500
0!
b0 "
b0 (
b0 *
0$
#2000
0%
#3000
1%
#3500
1$
#4000
0%
#5000
1%
#5500
1'
#6000
0%
#7000
b1 "
b1 (
b1 *
1%
#8000
0%
#9000
b10 "
b10 (
b10 *
1%
#10000
0%
#11000
b11 "
b11 (
b11 *
1%
#11500
0'
#12000
0%
#13000
1%
#14000
0%
#15000
1%
#15500
1'
#16000
0%
#17000
1!
b0 "
b0 (
b100 *
1%
#17500
1&
#18000
0%
#19000
0!
b0 *
1%
#20000
0%
#20500
0&
#21000
b1 "
b1 (
b1 *
1%
#22000
0%
#23000
b10 "
b10 (
b10 *
1%
#24000
0%
#25000
b11 "
b11 (
b11 *
1%
#26000
0%
#27000
1!
b0 "
b0 (
b100 *
1%
#28000
0%
#29000
b1 "
b1 (
b101 *
1%
#30000
0%
#31000
b10 "
b10 (
b110 *
1%
